fcin-1.3.4.dist-info/licenses/LICENSE
funcoin/__init__.py
funcoin/funcoin.py
funcoin/funcoin_auxiliary.py
funcoin/graphics.py
funcoin/preproc.py
funcoin/temp_storage.py
fcin-1.3.4.dist-info/METADATA
fcin-1.3.4.dist-info/WHEEL
fcin-1.3.4.dist-info/top_level.txt
fcin-1.3.4.dist-info/RECORD
