Metadata-Version: 2.4
Name: fcin
Version: 1.3.4
Summary: Functional Connectivity Integrative Normative Modelling (FUNCOIN).
Home-page: https://github.com/kobbersmed/funcoin
Author: Janus R. L. Kobbersmed
Author-email: janus@cfin.au.dk
License: GPL-3.0-or-later
Classifier: Intended Audience :: Science/Research
Classifier: Programming Language :: Python :: 3
Classifier: License :: OSI Approved :: GNU General Public License v3 or later (GPLv3+)
Requires-Python: >=3.6
License-File: LICENSE
Requires-Dist: numpy
Requires-Dist: scikit-learn
Requires-Dist: scipy
Requires-Dist: matplotlib
Requires-Dist: notebook
Dynamic: license-file
